Fulladder/design.sv
// Code your design here
`timescale 1ns/1ns
module fulladder(s,cout,a,b,cin);
    input a,b,cin;
    output s,cout;
    assign s = a^b^cin;
    assign cout = a&&b || a&&cin || b&&cin;

endmodule

Fulladder/testbench.sv
`timescale 1ns/1ns
module fulladdertb();
  reg a,b,cin;
  wire sum, cout;
  fulladder fa(sum,cout, a,b, cin);

  initial begin
    $dumpfile("dump.vcd"); 
    $dumpvars(1,fulladdertb);
    a=0;
    b=0;
    cin=0;
    #10
    $display("a = %d, b = %d, cin = %d, sum = %d, cout = %d",a,b,cin,sum,cout);
    a=0;
    b=0;
    cin=1;
    #10
    $display("a = %d, b = %d, cin = %d, sum = %d, cout = %d",a,b,cin,sum,cout);
    a=0;
    b=1;
    cin=0;
    #10
    $display("a = %d, b = %d, cin = %d, sum = %d, cout = %d",a,b,cin,sum, cout);
    a=0;
    b=1;    
    cin=1;
    #10
    $display("a = %d, b = %d, cin = %d, sum = %d, cout = %d",a,b,cin,sum, cout);
	a=1;
    b=0;    
    cin=0;
    #10
    $display("a = %d, b = %d, cin = %d, sum = %d, cout = %d",a,b,cin,sum, cout);
    a=1;
    b=0;    
    cin=1;
    #10
    $display("a = %d, b = %d, cin = %d, sum = %d, cout = %d",a,b,cin,sum, cout);
    a=1;
    b=1;    
    cin=0;
    #10
    $display("a = %d, b = %d, cin = %d, sum = %d, cout = %d",a,b,cin,sum, cout);
    a=1;
    b=1;    
    cin=1;
    #10
    $display("a = %d, b = %d, cin = %d, sum = %d, cout = %d",a,b,cin,sum, cout);
    $finish;
  end
endmodule

Fulladder/dump.vcd
$date
	Wed Jul 27 14:17:41 2022
$end
$version
	Icarus Verilog
$end
$timescale
	1ns
$end
$scope module fulladdertb $end
$var wire 1 ! sum $end
$var wire 1 " cout $end
$var reg 1 # a $end
$var reg 1 $ b $end
$var reg 1 % cin $end
$upscope $end
$enddefinitions $end
#0
$dumpvars
0%
0$
0#
0"
0!
$end
#10
1!
1%
#20
0%
1$
#30
1"
0!
1%
#40
0"
1!
0%
0$
1#
#50
1"
0!
1%
#60
0%
1$
#70
1!
1%
